<archimate:ArchimateDiagramModel
    xmlns:xsi="http://www.w3.org/2001/XMLSchema-instance"
    xmlns:archimate="http://www.archimatetool.com/archimate"
    name="ARC Server Student Attendance Monitoring Stage 1"
    id="id-28051">
  <children
      xsi:type="archimate:DiagramModelArchimateObject"
      id="id-59559"
      font="1|Arial|10.0|0|WINDOWS|1|0|0|0|0|0|0|0|0|1|0|0|0|0|Arial"
      fontColor="#000000"
      lineColor="#707070"
      fillColor="#fbb875">
    <sourceConnections
        xsi:type="archimate:DiagramModelArchimateConnection"
        id="id-16fc202405bd480a98898e337c15cc6c"
        source="id-59559"
        target="id-59560">
      <archimateRelationship
          xsi:type="archimate:AssignmentRelationship"
          href="AssignmentRelationship_id-69501.xml#id-69501"/>
    </sourceConnections>
    <sourceConnections
        xsi:type="archimate:DiagramModelArchimateConnection"
        id="id-f36d6e046cef49bd878a762500aeae66"
        source="id-59559"
        target="id-59564">
      <archimateRelationship
          xsi:type="archimate:AssignmentRelationship"
          href="AssignmentRelationship_id-69727.xml#id-69727"/>
    </sourceConnections>
    <bounds
        x="324"
        y="372"
        width="433"
        height="361"/>
    <children
        xsi:type="archimate:DiagramModelArchimateObject"
        id="id-59560"
        targetConnections="id-16fc202405bd480a98898e337c15cc6c"
        font="1|Segoe UI|10.0|0|WINDOWS|1|0|0|0|0|0|0|0|0|1|0|0|0|0|Segoe UI"
        fontColor="#000000"
        lineColor="#707070"
        fillColor="#c9e7b7">
      <sourceConnections
          xsi:type="archimate:DiagramModelArchimateConnection"
          id="id-e962d57564db43cabfc5653f5f30749c"
          source="id-59560"
          target="id-59562">
        <archimateRelationship
            xsi:type="archimate:AggregationRelationship"
            href="AggregationRelationship_id-60439.xml#id-60439"/>
      </sourceConnections>
      <bounds
          x="24"
          y="36"
          width="181"
          height="133"/>
      <children
          xsi:type="archimate:DiagramModelArchimateObject"
          id="id-59562"
          targetConnections="id-e962d57564db43cabfc5653f5f30749c"
          font="1|Segoe UI|10.0|0|WINDOWS|1|0|0|0|0|0|0|0|0|1|0|0|0|0|Segoe UI"
          fontColor="#000000"
          lineColor="#707070"
          fillColor="#c9e7b7">
        <sourceConnections
            xsi:type="archimate:DiagramModelArchimateConnection"
            id="id-59599"
            font="1|Arial|10.0|0|WINDOWS|1|0|0|0|0|0|0|0|0|1|0|0|0|0|Arial"
            fontColor="#000000"
            lineColor="#808080"
            source="id-59562"
            target="id-59570">
          <archimateRelationship
              xsi:type="archimate:AccessRelationship"
              href="AccessRelationship_id-59600.xml#id-59600"/>
        </sourceConnections>
        <sourceConnections
            xsi:type="archimate:DiagramModelArchimateConnection"
            id="id-59590"
            font="1|Arial|10.0|0|WINDOWS|1|0|0|0|0|0|0|0|0|1|0|0|0|0|Arial"
            fontColor="#000000"
            lineColor="#626262"
            source="id-59562"
            target="id-59565">
          <archimateRelationship
              xsi:type="archimate:AccessRelationship"
              href="AccessRelationship_id-59591.xml#id-59591"/>
        </sourceConnections>
        <bounds
            x="24"
            y="36"
            width="133"
            height="49"/>
        <archimateElement
            xsi:type="archimate:SystemSoftware"
            href="SystemSoftware_id-59563.xml#id-59563"/>
      </children>
      <archimateElement
          xsi:type="archimate:Node"
          href="Node_id-59561.xml#id-59561"/>
    </children>
    <children
        xsi:type="archimate:DiagramModelArchimateObject"
        id="id-59564"
        targetConnections="id-f36d6e046cef49bd878a762500aeae66"
        font="1|Segoe UI|10.0|0|WINDOWS|1|0|0|0|0|0|0|0|0|1|0|0|0|0|Segoe UI"
        fontColor="#000000"
        lineColor="#707070"
        fillColor="#c9e7b7">
      <sourceConnections
          xsi:type="archimate:DiagramModelArchimateConnection"
          id="id-59592"
          font="1|Arial|10.0|0|WINDOWS|1|0|0|0|0|0|0|0|0|1|0|0|0|0|Arial"
          fontColor="#000000"
          lineColor="#626262"
          source="id-59564"
          target="id-59579">
        <archimateRelationship
            xsi:type="archimate:ServingRelationship"
            href="ServingRelationship_id-59593.xml#id-59593"/>
      </sourceConnections>
      <bounds
          x="216"
          y="240"
          width="181"
          height="85"/>
      <children
          xsi:type="archimate:DiagramModelArchimateObject"
          id="id-59565"
          targetConnections="id-59590"
          font="1|Segoe UI|10.0|0|WINDOWS|1|0|0|0|0|0|0|0|0|1|0|0|0|0|Segoe UI"
          fontColor="#000000"
          lineColor="#707070"
          fillColor="#c9e7b7">
        <bounds
            y="36"
            width="157"
            height="49"/>
        <archimateElement
            xsi:type="archimate:Artifact"
            href="Artifact_id-59566.xml#id-59566"/>
      </children>
      <archimateElement
          xsi:type="archimate:TechnologyService"
          href="TechnologyService_id-30122.xml#id-30122"/>
    </children>
    <children
        xsi:type="archimate:DiagramModelNote"
        id="id-59882"
        font="1|Segoe UI|10.0|0|WINDOWS|1|0|0|0|0|0|0|0|0|1|0|0|0|0|Segoe UI"
        fontColor="#000000"
        lineColor="#707070"
        textAlignment="1"
        fillColor="#ffffff"
        content="Overnight data upload">
      <bounds
          x="84"
          y="192"
          width="157"
          height="25"/>
    </children>
    <children
        xsi:type="archimate:DiagramModelNote"
        id="id-59884"
        font="1|Segoe UI|10.0|0|WINDOWS|1|0|0|0|0|0|0|0|0|1|0|0|0|0|Segoe UI"
        fontColor="#000000"
        lineColor="#707070"
        textAlignment="1"
        fillColor="#8080ff"
        content="STABILISE Put SQL on centrally support SQL Server Infrastructure">
      <bounds
          x="252"
          y="144"
          width="157"
          height="97"/>
    </children>
    <children
        xsi:type="archimate:DiagramModelNote"
        id="id-59886"
        font="1|Segoe UI|10.0|0|WINDOWS|1|0|0|0|0|0|0|0|0|1|0|0|0|0|Segoe UI"
        fontColor="#000000"
        lineColor="#707070"
        textAlignment="1"
        fillColor="#8080ff"
        content="STABILISE: Sign initial 1 year SLA with ARC">
      <bounds
          x="204"
          y="48"
          width="181"
          height="73"/>
    </children>
    <archimateElement
        xsi:type="archimate:Location"
        href="Location_id-29693.xml#id-29693"/>
  </children>
  <children
      xsi:type="archimate:DiagramModelArchimateObject"
      id="id-59567"
      font="1|Segoe UI|10.0|0|WINDOWS|1|0|0|0|0|0|0|0|0|1|0|0|0|0|Segoe UI"
      fontColor="#000000"
      lineColor="#707070"
      fillColor="#fbb875">
    <sourceConnections
        xsi:type="archimate:DiagramModelArchimateConnection"
        id="id-9deacc1bb5eb4f369610fe8774aa31b2"
        source="id-59567"
        target="id-59568">
      <archimateRelationship
          xsi:type="archimate:AssignmentRelationship"
          href="AssignmentRelationship_id-69578.xml#id-69578"/>
    </sourceConnections>
    <sourceConnections
        xsi:type="archimate:DiagramModelArchimateConnection"
        id="id-42932bd46ae340dbb939cfcb11e823f7"
        source="id-59567"
        target="id-59574">
      <archimateRelationship
          xsi:type="archimate:AssignmentRelationship"
          href="AssignmentRelationship_id-69492.xml#id-69492"/>
    </sourceConnections>
    <sourceConnections
        xsi:type="archimate:DiagramModelArchimateConnection"
        id="id-c9bcff75c8bb4019ad0d736cbb47e7bf"
        source="id-59567"
        target="id-59572">
      <archimateRelationship
          xsi:type="archimate:AssignmentRelationship"
          href="AssignmentRelationship_id-69421.xml#id-69421"/>
    </sourceConnections>
    <sourceConnections
        xsi:type="archimate:DiagramModelArchimateConnection"
        id="id-ddfd5adea0cb494daacf02507b395432"
        source="id-59567"
        target="id-59576">
      <archimateRelationship
          xsi:type="archimate:AssignmentRelationship"
          href="AssignmentRelationship_id-69522.xml#id-69522"/>
    </sourceConnections>
    <bounds
        x="60"
        y="168"
        width="673"
        height="169"/>
    <children
        xsi:type="archimate:DiagramModelArchimateObject"
        id="id-59568"
        targetConnections="id-59598 id-59594 id-59596 id-59602 id-9deacc1bb5eb4f369610fe8774aa31b2"
        font="1|Segoe UI|10.0|0|WINDOWS|1|0|0|0|0|0|0|0|0|1|0|0|0|0|Segoe UI"
        fontColor="#000000"
        lineColor="#707070"
        fillColor="#c9e7b7">
      <sourceConnections
          xsi:type="archimate:DiagramModelArchimateConnection"
          id="id-1f58b5c177394773b9b41cc45f5b5917"
          source="id-59568"
          target="id-59570">
        <archimateRelationship
            xsi:type="archimate:AssignmentRelationship"
            href="AssignmentRelationship_id-60678.xml#id-60678"/>
      </sourceConnections>
      <bounds
          x="12"
          y="12"
          width="121"
          height="121"/>
      <children
          xsi:type="archimate:DiagramModelArchimateObject"
          id="id-59570"
          targetConnections="id-59599 id-1f58b5c177394773b9b41cc45f5b5917"
          font="1|Segoe UI|10.0|0|WINDOWS|1|0|0|0|0|0|0|0|0|1|0|0|0|0|Segoe UI"
          fontColor="#000000"
          lineColor="#707070"
          fillColor="#ff0000">
        <bounds
            y="48"
            width="121"
            height="49"/>
        <archimateElement
            xsi:type="archimate:Artifact"
            href="Artifact_id-59571.xml#id-59571"/>
      </children>
      <archimateElement
          xsi:type="archimate:Device"
          href="Device_id-59569.xml#id-59569"/>
    </children>
    <children
        xsi:type="archimate:DiagramModelArchimateObject"
        id="id-59574"
        targetConnections="id-42932bd46ae340dbb939cfcb11e823f7"
        font="1|Segoe UI|10.0|0|WINDOWS|1|0|0|0|0|0|0|0|0|1|0|0|0|0|Segoe UI"
        fontColor="#000000"
        lineColor="#707070"
        fillColor="#c9e7b7">
      <sourceConnections
          xsi:type="archimate:DiagramModelArchimateConnection"
          id="id-59598"
          font="1|Arial|10.0|0|WINDOWS|1|0|0|0|0|0|0|0|0|1|0|0|0|0|Arial"
          fontColor="#000000"
          lineColor="#626262"
          source="id-59574"
          target="id-59568">
        <archimateRelationship
            xsi:type="archimate:AssociationRelationship"
            href="AssociationRelationship_id-59595.xml#id-59595"/>
      </sourceConnections>
      <sourceConnections
          xsi:type="archimate:DiagramModelArchimateConnection"
          id="id-59594"
          font="1|Arial|10.0|0|WINDOWS|1|0|0|0|0|0|0|0|0|1|0|0|0|0|Arial"
          fontColor="#000000"
          lineColor="#626262"
          source="id-59574"
          target="id-59568">
        <archimateRelationship
            xsi:type="archimate:AssociationRelationship"
            href="AssociationRelationship_id-59595.xml#id-59595"/>
      </sourceConnections>
      <bounds
          x="168"
          y="24"
          width="85"
          height="49"/>
      <archimateElement
          xsi:type="archimate:Device"
          href="Device_id-59575.xml#id-59575"/>
    </children>
    <children
        xsi:type="archimate:DiagramModelArchimateObject"
        id="id-59572"
        targetConnections="id-c9bcff75c8bb4019ad0d736cbb47e7bf"
        font="1|Segoe UI|10.0|0|WINDOWS|1|0|0|0|0|0|0|0|0|1|0|0|0|0|Segoe UI"
        fontColor="#000000"
        lineColor="#707070"
        fillColor="#c9e7b7">
      <sourceConnections
          xsi:type="archimate:DiagramModelArchimateConnection"
          id="id-59596"
          font="1|Arial|10.0|0|WINDOWS|1|0|0|0|0|0|0|0|0|1|0|0|0|0|Arial"
          fontColor="#000000"
          lineColor="#626262"
          source="id-59572"
          target="id-59568">
        <archimateRelationship
            xsi:type="archimate:AssociationRelationship"
            href="AssociationRelationship_id-59597.xml#id-59597"/>
      </sourceConnections>
      <bounds
          x="228"
          y="24"
          width="85"
          height="61"/>
      <archimateElement
          xsi:type="archimate:Device"
          href="Device_id-59573.xml#id-59573"/>
    </children>
    <children
        xsi:type="archimate:DiagramModelArchimateObject"
        id="id-59576"
        targetConnections="id-ddfd5adea0cb494daacf02507b395432"
        font="1|Segoe UI|10.0|0|WINDOWS|1|0|0|0|0|0|0|0|0|1|0|0|0|0|Segoe UI"
        fontColor="#000000"
        lineColor="#707070"
        fillColor="#c9e7b7">
      <sourceConnections
          xsi:type="archimate:DiagramModelArchimateConnection"
          id="id-59602"
          font="1|Arial|10.0|0|WINDOWS|1|0|0|0|0|0|0|0|0|1|0|0|0|0|Arial"
          fontColor="#000000"
          lineColor="#626262"
          source="id-59576"
          target="id-59568">
        <bendpoints
            startX="-156"
            endX="156"
            endY="-12"/>
        <archimateRelationship
            xsi:type="archimate:AssociationRelationship"
            href="AssociationRelationship_id-59603.xml#id-59603"/>
      </sourceConnections>
      <sourceConnections
          xsi:type="archimate:DiagramModelArchimateConnection"
          id="id-59605"
          font="1|Arial|10.0|0|WINDOWS|1|0|0|0|0|0|0|0|0|1|0|0|0|0|Arial"
          fontColor="#000000"
          lineColor="#626262"
          source="id-59576"
          target="id-59581">
        <archimateRelationship
            xsi:type="archimate:ServingRelationship"
            href="ServingRelationship_id-59606.xml#id-59606"/>
      </sourceConnections>
      <bounds
          x="312"
          y="24"
          width="145"
          height="73"/>
      <children
          xsi:type="archimate:DiagramModelNote"
          id="id-59894"
          font="1|Segoe UI|10.0|0|WINDOWS|1|0|0|0|0|0|0|0|0|1|0|0|0|0|Segoe UI"
          fontColor="#000000"
          lineColor="#707070"
          textAlignment="1"
          fillColor="#ff0000"
          content="Modified by Arc">
        <bounds
            x="12"
            y="24"
            width="121"
            height="25"/>
      </children>
      <archimateElement
          xsi:type="archimate:Device"
          href="Device_id-59577.xml#id-59577"/>
    </children>
    <children
        xsi:type="archimate:DiagramModelNote"
        id="id-59896"
        font="1|Segoe UI|10.0|0|WINDOWS|1|0|0|0|0|0|0|0|0|1|0|0|0|0|Segoe UI"
        fontColor="#000000"
        lineColor="#707070"
        textAlignment="1"
        fillColor="#ffffff"
        content="Flash memory stores Student Id (from Student Card) + Time + Room Location (via fixed Card Reader IP address)&#xA;&#xA;End of life">
      <bounds
          x="324"
          y="84"
          width="253"
          height="85"/>
    </children>
    <children
        xsi:type="archimate:DiagramModelNote"
        id="id-59898"
        font="1|Segoe UI|10.0|0|WINDOWS|1|0|0|0|0|0|0|0|0|1|0|0|0|0|Segoe UI"
        fontColor="#000000"
        lineColor="#707070"
        textAlignment="1"
        fillColor="#8080ff"
        content="STABILISE: Hand Reader and ARC documentation over to central support team">
      <bounds
          x="468"
          width="169"
          height="85"/>
    </children>
    <archimateElement
        xsi:type="archimate:Location"
        href="Location_id-49306.xml#id-49306"/>
  </children>
  <children
      xsi:type="archimate:DiagramModelArchimateObject"
      id="id-59578"
      font="1|Segoe UI|10.0|0|WINDOWS|1|0|0|0|0|0|0|0|0|1|0|0|0|0|Segoe UI"
      fontColor="#000000"
      lineColor="#707070"
      fillColor="#b5ffff">
    <bounds
        x="36"
        y="396"
        width="157"
        height="126"/>
    <children
        xsi:type="archimate:DiagramModelNote"
        id="id-59901"
        font="1|Segoe UI|10.0|0|WINDOWS|1|0|0|0|0|0|0|0|0|1|0|0|0|0|Segoe UI"
        fontColor="#000000"
        lineColor="#707070"
        textAlignment="1"
        fillColor="#ffffff"
        content="Separate system also owned by ARC">
      <bounds
          x="24"
          y="72"
          width="121"
          height="49"/>
    </children>
    <archimateElement
        xsi:type="archimate:ApplicationComponent"
        href="ApplicationComponent_id-43807.xml#id-43807"/>
  </children>
  <children
      xsi:type="archimate:DiagramModelArchimateObject"
      id="id-59579"
      targetConnections="id-59592 id-59614 id-59613"
      font="1|Segoe UI|10.0|0|WINDOWS|1|0|0|0|0|0|0|0|0|1|0|0|0|0|Segoe UI"
      fontColor="#000000"
      lineColor="#707070"
      fillColor="#b5ffff">
    <sourceConnections
        xsi:type="archimate:DiagramModelArchimateConnection"
        id="id-59601"
        font="1|Arial|10.0|0|WINDOWS|1|0|0|0|0|0|0|0|0|1|0|0|0|0|Arial"
        fontColor="#000000"
        lineColor="#626262"
        source="id-59579"
        target="id-59587">
      <archimateRelationship
          xsi:type="archimate:ServingRelationship"
          href="ServingRelationship_id-55662.xml#id-55662"/>
    </sourceConnections>
    <bounds
        x="768"
        y="372"
        width="181"
        height="121"/>
    <children
        xsi:type="archimate:DiagramModelNote"
        id="id-59904"
        font="1|Segoe UI|10.0|0|WINDOWS|1|0|0|0|0|0|0|0|0|1|0|0|0|0|Segoe UI"
        fontColor="#000000"
        lineColor="#707070"
        textAlignment="1"
        fillColor="#ffffff"
        content="Written in-house">
      <bounds
          x="60"
          y="60"
          width="85"
          height="49"/>
    </children>
    <archimateElement
        xsi:type="archimate:ApplicationComponent"
        href="ApplicationComponent_id-55663.xml#id-55663"/>
  </children>
  <children
      xsi:type="archimate:DiagramModelArchimateObject"
      id="id-59583"
      font="1|Segoe UI|10.0|0|WINDOWS|1|0|0|0|0|0|0|0|0|1|0|0|0|0|Segoe UI"
      fontColor="#000000"
      lineColor="#707070"
      fillColor="#b5ffff">
    <sourceConnections
        xsi:type="archimate:DiagramModelArchimateConnection"
        id="id-59604"
        font="1|Arial|10.0|0|WINDOWS|1|0|0|0|0|0|0|0|0|1|0|0|0|0|Arial"
        fontColor="#000000"
        lineColor="#626262"
        source="id-59583"
        target="id-59585">
      <archimateRelationship
          xsi:type="archimate:ServingRelationship"
          href="ServingRelationship_id-55669.xml#id-55669"/>
    </sourceConnections>
    <sourceConnections
        xsi:type="archimate:DiagramModelArchimateConnection"
        id="id-59607"
        font="1|Arial|10.0|0|WINDOWS|1|0|0|0|0|0|0|0|0|1|0|0|0|0|Arial"
        fontColor="#000000"
        lineColor="#626262"
        source="id-59583"
        target="id-59589">
      <archimateRelationship
          xsi:type="archimate:FlowRelationship"
          href="FlowRelationship_id-55677.xml#id-55677"/>
    </sourceConnections>
    <bounds
        x="1116"
        y="372"
        width="180"
        height="121"/>
    <archimateElement
        xsi:type="archimate:ApplicationComponent"
        href="ApplicationComponent_id-28818.xml#id-28818"/>
  </children>
  <children
      xsi:type="archimate:DiagramModelArchimateObject"
      id="id-59582"
      font="1|Segoe UI|10.0|0|WINDOWS|1|0|0|0|0|0|0|0|0|1|0|0|0|0|Segoe UI"
      fontColor="#000000"
      lineColor="#707070"
      fillColor="#ffffb5">
    <sourceConnections
        xsi:type="archimate:DiagramModelArchimateConnection"
        id="id-59611"
        font="1|Arial|10.0|0|WINDOWS|1|0|0|0|0|0|0|0|0|1|0|0|0|0|Arial"
        fontColor="#000000"
        lineColor="#626262"
        source="id-59582"
        target="id-59585">
      <archimateRelationship
          xsi:type="archimate:AssignmentRelationship"
          href="AssignmentRelationship_id-49253.xml#id-49253"/>
    </sourceConnections>
    <sourceConnections
        xsi:type="archimate:DiagramModelArchimateConnection"
        id="id-59608"
        font="1|Arial|10.0|0|WINDOWS|1|0|0|0|0|0|0|0|0|1|0|0|0|0|Arial"
        fontColor="#000000"
        lineColor="#626262"
        source="id-59582"
        target="id-59587">
      <archimateRelationship
          xsi:type="archimate:AssignmentRelationship"
          href="AssignmentRelationship_id-49256.xml#id-49256"/>
    </sourceConnections>
    <bounds
        x="1008"
        y="12"
        width="181"
        height="61"/>
    <archimateElement
        xsi:type="archimate:BusinessRole"
        href="BusinessRole_id-49255.xml#id-49255"/>
  </children>
  <children
      xsi:type="archimate:DiagramModelArchimateObject"
      id="id-59580"
      font="1|Segoe UI|10.0|0|WINDOWS|1|0|0|0|0|0|0|0|0|1|0|0|0|0|Segoe UI"
      fontColor="#000000"
      lineColor="#707070"
      fillColor="#ffffb5">
    <sourceConnections
        xsi:type="archimate:DiagramModelArchimateConnection"
        id="id-59610"
        font="1|Arial|10.0|0|WINDOWS|1|0|0|0|0|0|0|0|0|1|0|0|0|0|Arial"
        fontColor="#000000"
        lineColor="#626262"
        source="id-59580"
        target="id-59581">
      <archimateRelationship
          xsi:type="archimate:AssignmentRelationship"
          href="AssignmentRelationship_id-49252.xml#id-49252"/>
    </sourceConnections>
    <bounds
        x="408"
        width="84"
        height="72"/>
    <archimateElement
        xsi:type="archimate:BusinessActor"
        href="BusinessActor_id-28698.xml#id-28698"/>
  </children>
  <children
      xsi:type="archimate:DiagramModelArchimateObject"
      id="id-59581"
      targetConnections="id-59605 id-59610"
      font="1|Segoe UI|10.0|0|WINDOWS|1|0|0|0|0|0|0|0|0|1|0|0|0|0|Segoe UI"
      fontColor="#000000"
      lineColor="#707070"
      fillColor="#ffffb5">
    <sourceConnections
        xsi:type="archimate:DiagramModelArchimateConnection"
        id="id-59609"
        font="1|Arial|10.0|0|WINDOWS|1|0|0|0|0|0|0|0|0|1|0|0|0|0|Arial"
        fontColor="#000000"
        lineColor="#626262"
        source="id-59581"
        target="id-59584">
      <archimateRelationship
          xsi:type="archimate:AssociationRelationship"
          href="AssociationRelationship_id-49242.xml#id-49242"/>
    </sourceConnections>
    <bounds
        x="408"
        y="84"
        width="84"
        height="48"/>
    <archimateElement
        xsi:type="archimate:BusinessProcess"
        href="BusinessProcess_id-49244.xml#id-49244"/>
  </children>
  <children
      xsi:type="archimate:DiagramModelArchimateObject"
      id="id-59584"
      targetConnections="id-59609"
      font="1|Segoe UI|10.0|0|WINDOWS|1|0|0|0|0|0|0|0|0|1|0|0|0|0|Segoe UI"
      fontColor="#000000"
      lineColor="#707070"
      fillColor="#ffffb5">
    <bounds
        x="528"
        y="84"
        width="84"
        height="60"/>
    <archimateElement
        xsi:type="archimate:Product"
        href="Product_id-49243.xml#id-49243"/>
  </children>
  <children
      xsi:type="archimate:DiagramModelArchimateObject"
      id="id-59585"
      targetConnections="id-59604 id-59611"
      font="1|Segoe UI|10.0|0|WINDOWS|1|0|0|0|0|0|0|0|0|1|0|0|0|0|Segoe UI"
      fontColor="#000000"
      lineColor="#707070"
      fillColor="#ffffb5">
    <bounds
        x="1044"
        y="96"
        width="144"
        height="48"/>
    <archimateElement
        xsi:type="archimate:BusinessProcess"
        href="BusinessProcess_id-49254.xml#id-49254"/>
  </children>
  <children
      xsi:type="archimate:DiagramModelNote"
      id="id-59912"
      font="1|Segoe UI|10.0|0|WINDOWS|1|0|0|0|0|0|0|0|0|1|0|0|0|0|Segoe UI"
      fontColor="#000000"
      lineColor="#707070"
      textAlignment="1"
      fillColor="#ffffff"
      content="Done retrospectively where academic hasn't updated room change in advance">
    <bounds
        x="1188"
        y="96"
        width="132"
        height="96"/>
  </children>
  <children
      xsi:type="archimate:DiagramModelArchimateObject"
      id="id-59587"
      targetConnections="id-59601 id-59608"
      font="1|Segoe UI|10.0|0|WINDOWS|1|0|0|0|0|0|0|0|0|1|0|0|0|0|Segoe UI"
      fontColor="#000000"
      lineColor="#707070"
      fillColor="#ffffb5">
    <bounds
        x="792"
        y="96"
        width="156"
        height="48"/>
    <archimateElement
        xsi:type="archimate:BusinessProcess"
        href="BusinessProcess_id-49257.xml#id-49257"/>
  </children>
  <children
      xsi:type="archimate:DiagramModelArchimateObject"
      id="id-59586"
      font="1|Segoe UI|10.0|0|WINDOWS|1|0|0|0|0|0|0|0|0|1|0|0|0|0|Segoe UI"
      fontColor="#000000"
      lineColor="#707070"
      fillColor="#b5ffff">
    <sourceConnections
        xsi:type="archimate:DiagramModelArchimateConnection"
        id="id-59612"
        font="1|Arial|10.0|0|WINDOWS|1|0|0|0|0|0|0|0|0|1|0|0|0|0|Arial"
        fontColor="#000000"
        lineColor="#626262"
        source="id-59586"
        target="id-59588">
      <archimateRelationship
          xsi:type="archimate:FlowRelationship"
          href="FlowRelationship_id-55660.xml#id-55660"/>
    </sourceConnections>
    <bounds
        x="1116"
        y="564"
        width="180"
        height="132"/>
    <archimateElement
        xsi:type="archimate:ApplicationComponent"
        href="ApplicationComponent_id-29401.xml#id-29401"/>
  </children>
  <children
      xsi:type="archimate:DiagramModelArchimateObject"
      id="id-59589"
      targetConnections="id-59607"
      font="1|Segoe UI|10.0|0|WINDOWS|1|0|0|0|0|0|0|0|0|1|0|0|0|0|Segoe UI"
      fontColor="#000000"
      lineColor="#707070"
      fillColor="#b5ffff">
    <sourceConnections
        xsi:type="archimate:DiagramModelArchimateConnection"
        id="id-59614"
        font="1|Arial|10.0|0|WINDOWS|1|0|0|0|0|0|0|0|0|1|0|0|0|0|Arial"
        fontColor="#000000"
        lineColor="#626262"
        source="id-59589"
        target="id-59579">
      <archimateRelationship
          xsi:type="archimate:FlowRelationship"
          href="FlowRelationship_id-55664.xml#id-55664"/>
    </sourceConnections>
    <bounds
        x="984"
        y="408"
        width="108"
        height="72"/>
    <archimateElement
        xsi:type="archimate:ApplicationInterface"
        href="ApplicationInterface_id-55665.xml#id-55665"/>
  </children>
  <children
      xsi:type="archimate:DiagramModelArchimateObject"
      id="id-59588"
      targetConnections="id-59612"
      font="1|Segoe UI|10.0|0|WINDOWS|1|0|0|0|0|0|0|0|0|1|0|0|0|0|Segoe UI"
      fontColor="#000000"
      lineColor="#707070"
      fillColor="#b5ffff">
    <sourceConnections
        xsi:type="archimate:DiagramModelArchimateConnection"
        id="id-59613"
        font="1|Arial|10.0|0|WINDOWS|1|0|0|0|0|0|0|0|0|1|0|0|0|0|Arial"
        fontColor="#000000"
        lineColor="#626262"
        source="id-59588"
        target="id-59579">
      <archimateRelationship
          xsi:type="archimate:FlowRelationship"
          href="FlowRelationship_id-55676.xml#id-55676"/>
    </sourceConnections>
    <bounds
        x="984"
        y="492"
        width="108"
        height="60"/>
    <archimateElement
        xsi:type="archimate:ApplicationInterface"
        href="ApplicationInterface_id-55661.xml#id-55661"/>
  </children>
  <children
      xsi:type="archimate:DiagramModelNote"
      id="id-59918"
      font="1|Segoe UI|10.0|0|WINDOWS|1|0|0|0|0|0|0|0|0|1|0|0|0|0|Segoe UI"
      fontColor="#000000"
      lineColor="#707070"
      textAlignment="1"
      fillColor="#ff0000"
      content="Manual">
    <bounds
        x="996"
        y="552"
        width="72"
        height="36"/>
  </children>
  <children
      xsi:type="archimate:DiagramModelNote"
      id="id-59920"
      font="1|Segoe UI|10.0|0|WINDOWS|1|0|0|0|0|0|0|0|0|1|0|0|0|0|Segoe UI"
      fontColor="#000000"
      lineColor="#707070"
      textAlignment="1"
      fillColor="#ffffff"
      content="TO BE First Stage&#xA;&#xA;(this is a stabilisation stage, see the blue boxes for info)">
    <bounds
        x="60"
        width="157"
        height="85"/>
  </children>
  <children
      xsi:type="archimate:DiagramModelNote"
      id="id-59922"
      font="1|Segoe UI|10.0|0|WINDOWS|1|0|0|0|0|0|0|0|0|1|0|0|0|0|Segoe UI"
      fontColor="#000000"
      lineColor="#707070"
      textAlignment="1"
      fillColor="#8080ff"
      content="STABILISE Hand this reporting tool over to Data team">
    <bounds
        x="780"
        y="276"
        width="169"
        height="97"/>
  </children>
</archimate:ArchimateDiagramModel>
